kefir
