Metadata-Version: 2.1
Name: kefir
Version: 0.1.3
Summary: Kefir is a natural language processing kit for Turkic languages
Home-page: https://github.com/yogurt-cultures/kefir
Author: Yogurt Cultures
Author-email: cediddi@gmail.com
License: MIT
Platform: UNKNOWN
Classifier: License :: OSI Approved :: MIT License
Classifier: Programming Language :: Python
Classifier: Programming Language :: Python :: 3
Classifier: Programming Language :: Python :: 3.6
Classifier: Programming Language :: Python :: Implementation :: CPython
Classifier: Topic :: Text Processing :: Linguistic
Classifier: Natural Language :: Turkish
Classifier: Development Status :: 3 - Alpha
Classifier: Intended Audience :: Developers
Classifier: Intended Audience :: Information Technology
